{
  "sentences": [
    {
      "words": [
        5,
        15,
        1,
        6,
        9,
        98,
        5,
        0
      ],
      "size": 8
    },
    {
      "words": [
        6,
        10,
        44,
        0,
        0,
        0,
        0,
        0
      ],
      "size": 8
    },
    {
      "words": [
        5,
        2,
        15,
        5,
        12,
        6,
        44,
        0
      ],
      "size": 8
    },
    {
      "words": [
        5,
        10,
        15,
        6,
        0,
        0,
        0,
        0
      ],
      "size": 8
    }
  ],
  "types": [
    0,
    0,
    0,
    0
  ],
  "requirements": [
    0,
    0,
    0,
    0
  ],
  "status": 1,
  "condition": []
}